cftsdata/__init__.py
cftsdata/abr.py
cftsdata/api.py
cftsdata/dataset.py
cftsdata/dpoae.py
cftsdata/efr.py
cftsdata/iec.py
cftsdata/inear_calibration.py
cftsdata/memr.py
cftsdata/microphone_calibration.py
cftsdata/postprocess.py
cftsdata/summarize_abr.py
cftsdata/summarize_abr_gui.enaml
cftsdata/summarize_dpoae.py
cftsdata/summarize_ecg.py
cftsdata/summarize_efr.py
cftsdata/summarize_iec.py
cftsdata/summarize_memr.py
cftsdata/summarize_memr_th.py
cftsdata/summarize_noise_exposure.py
cftsdata/util.py
cftsdata/version.py
cftsdata-0.1.7.dist-info/LICENSE.txt
cftsdata-0.1.7.dist-info/METADATA
cftsdata-0.1.7.dist-info/WHEEL
cftsdata-0.1.7.dist-info/entry_points.txt
cftsdata-0.1.7.dist-info/top_level.txt
cftsdata-0.1.7.dist-info/RECORD
