Metadata-Version: 2.2
Name: cftsdata
Version: 0.1.7
Summary: Lightweight tools for managing CFTS data
Author-email: Brad Buran <buran@ohsu.edu>, Brad Buran <bburan@alum.mit.edu>, "Buran Consulting, LLC" <info@bradburan.com>
Maintainer-email: Brad Buran <buran@ohsu.edu>, Brad Buran <bburan@alum.mit.edu>, "Buran Consulting, LLC" <info@bradburan.com>
License: MIT License
Requires-Python: >=3.7
License-File: LICENSE.txt
Requires-Dist: csaps
Requires-Dist: tqdm
Requires-Dist: palettable
Requires-Dist: psidata[zarr-backend]
Requires-Dist: psiaudio
Requires-Dist: jmespath
Requires-Dist: joblib
Provides-Extra: docs
Requires-Dist: sphinx; extra == "docs"
Requires-Dist: sphinx_rtd_theme; extra == "docs"
Requires-Dist: pygments-enaml; extra == "docs"
Provides-Extra: test
Requires-Dist: pytest; extra == "test"
Requires-Dist: pytest-console-scripts; extra == "test"
